{
    "agility": 3,
    "damageResistance": 1,
    "decisions": [
        {
            "ability": {
                "actionType": "ATTACK",
                "conditionType": "HIT_POINTS",
                "orderType": "MAX"
            },
            "preCondition": {
                "matchType": "ANY",
                "qualifiers": [
                    {
                        "actorCheckers": [
                            {
                                "conditionType": "HIT_POINTS",
                                "expressionType": "EXACT",
                                "operatorType": "GREATER_THAN",
                                "priorityType": "HIGHEST",
                                "value": 0
                            }
                        ],
                        "matchType": "ANY",
                        "priorityType": "HIGHEST",
                        "targetType": "ENEMY"
                    }
                ]
            },
            "priorityType": "LOWEST",
            "targetSelection": {
                "matchType": "ANY",
                "qualifiers": [
                    {
                        "actorCheckers": [
                            {
                                "conditionType": "HIT_POINTS",
                                "expressionType": "EXACT",
                                "operatorType": "GREATER_THAN",
                                "priorityType": "HIGHEST",
                                "value": 0
                            }
                        ],
                        "matchType": "ANY",
                        "priorityType": "HIGHEST",
                        "targetType": "ENEMY"
                    }
                ]
            }
        }
    ],
    "experiencePoints": 1,
    "goldPoints": 2,
    "hitPointsMaximum": 3,
    "id": "00",
    "name": "SLIME",
    "pattern": "0",
    "statusResistance": 15,
    "strength": 5
}